MANIFEST.in
info.py
requirements.txt
setup.py
version.py
dungeon_generator/Door.py
dungeon_generator/Frame.py
dungeon_generator/Generator.py
dungeon_generator/Rect.py
dungeon_generator/Road.py
dungeon_generator/Roads.py
dungeon_generator/Room.py
dungeon_generator/RoomSearcher.py
dungeon_generator/RoomSizeGenerator.py
dungeon_generator/Rooms.py
dungeon_generator/Tile.py
dungeon_generator/Util.py
dungeon_generator/Waterway.py
dungeon_generator/__init__.py
dungeon_generator.egg-info/PKG-INFO
dungeon_generator.egg-info/SOURCES.txt
dungeon_generator.egg-info/dependency_links.txt
dungeon_generator.egg-info/top_level.txt